{
  "_fv": 34,
  "_type": "recipe",
  "definition": {
    "recipeType": "Crafting",
    "xpReward": 0.0,
    "cookingTime": 200,
    "recipeRetstackSize": 5,
    "group": "",
    "recipeShapeless": true,
    "recipeSlots": [
      {
        "value": "CUSTOM:CopperIntaglio"
      },
      {
        "value": "Items.COPPER_INGOT"
      },
      {
        "value": ""
      },
      {
        "value": ""
      },
      {
        "value": ""
      },
      {
        "value": ""
      },
      {
        "value": ""
      },
      {
        "value": ""
      },
      {
        "value": ""
      }
    ],
    "recipeReturnStack": {
      "value": "CUSTOM:CopperCoin"
    },
    "name": "copper_coin_recipe",
    "namespace": "mod"
  }
}